visml/__init__.py
visml-0.0.1.dist-info/LICENSE.txt
visml-0.0.1.dist-info/METADATA
visml-0.0.1.dist-info/WHEEL
visml-0.0.1.dist-info/top_level.txt
visml-0.0.1.dist-info/RECORD
