Metadata-Version: 2.1
Name: visml
Version: 0.0.1
Summary: A Python package arraning methods for Machine Learning Visualization.
Home-page: UNKNOWN
Author: Mario Popolin Neto
License: Creative Commons Attribution-NonCommercial-ShareAlike 4.0 International
Platform: UNKNOWN
Classifier: License :: Free for non-commercial use
Classifier: Operating System :: OS Independent
Classifier: Programming Language :: Python :: 3.6
Requires-Python: >=3.6
Requires-Dist: numpy (>=1.16.0)
Requires-Dist: scikit-learn (>=0.20.0)
